.DS_Store
pythonabm/__init__.py
pythonabm/backend.py
pythonabm/simulation.py
pythonabm-0.3.3.dist-info/LICENSE.txt
pythonabm-0.3.3.dist-info/METADATA
pythonabm-0.3.3.dist-info/WHEEL
pythonabm-0.3.3.dist-info/top_level.txt
pythonabm-0.3.3.dist-info/RECORD
