Metadata-Version: 2.1
Name: pythonabm
Version: 0.3.3
Summary: Framework for building Agent-Based Models (ABMs) in Python
Author: Jack Toppen
Author-email: jtoppen3@gatech.edu
Requires-Python: >=3.7
License-File: LICENSE.txt
Requires-Dist: matplotlib
Requires-Dist: numpy (>=1.11)
Requires-Dist: numba
Requires-Dist: opencv-python
Requires-Dist: psutil
Requires-Dist: python-igraph
Requires-Dist: pyyaml
Requires-Dist: scipy
